{"actions": 3371, "added_lines": 205121.0, "added_lines_30": 4008.0, "added_lines_365": 205121.0, "added_lines_7": 127.0, "authors": 17, "authors_30": 7, "authors_365": 17, "authors_7": 3, "avg_commits_author": 34.35, "avg_commits_month": 64.89, "avg_files_author": 90.88, "avg_files_month": 171.67, "branches": 3, "commits": 584, "commits_30": 60, "commits_365": 584, "commits_7": 15, "committers": 17, "diff_netadded_lines_30": -68711.0, "diff_netadded_lines_365": 205121.0, "diff_netadded_lines_7": -2072.0, "diff_netauthors_30": -5, "diff_netauthors_365": 17, "diff_netauthors_7": 0, "diff_netcommits_30": -22, "diff_netcommits_365": 584, "diff_netcommits_7": 3, "diff_netfiles_30": -629, "diff_netfiles_365": 1545, "diff_netfiles_7": 172, "diff_netnewauthors_30": -2, "diff_netnewauthors_365": 17, "diff_netnewauthors_7": 0, "diff_netremoved_lines_30": -18422.0, "diff_netremoved_lines_365": 163077.0, "diff_netremoved_lines_7": 23471.0, "files": 1545, "files_30": 256, "files_365": 1545, "files_7": 201, "first_date": "2015-01-30", "last_date": "2015-11-25", "newauthors": 17, "newauthors_30": 0, "newauthors_365": 17, "newauthors_7": 0, "percentage_added_lines_30": 94, "percentage_added_lines_365": 0, "percentage_added_lines_7": 94, "percentage_authors_30": 41, "percentage_authors_365": 0, "percentage_authors_7": 0, "percentage_commits_30": 26, "percentage_commits_365": 0, "percentage_commits_7": 25, "percentage_files_30": 71, "percentage_files_365": 0, "percentage_files_7": 593, "percentage_newauthors_30": 100, "percentage_newauthors_365": 0, "percentage_newauthors_7": 0, "percentage_removed_lines_30": 40, "percentage_removed_lines_365": 0, "percentage_removed_lines_7": 1842, "removed_lines": 163077.0, "removed_lines_30": 27075.0, "removed_lines_365": 163077.0, "removed_lines_7": 24745.0, "repositories": 15}