{"allhistory_participants": 163, "bmitickets": 36.22, "bmitickets_30": 75, "bmitickets_365": 36, "bmitickets_7": 40, "changed": 1534, "changed_30": 492, "changed_365": 1534, "changed_7": 72, "changers": 137, "changers_30": 65, "changers_365": 137, "changers_7": 25, "closed": 607, "closed_30": 129, "closed_365": 607, "closed_7": 10, "closers": 50, "closers_30": 20, "closers_365": 50, "closers_7": 4, "diff_netbmitickets_30": 45, "diff_netbmitickets_365": 36, "diff_netbmitickets_7": -8, "diff_netchanged_30": -495, "diff_netchanged_365": 1534, "diff_netchanged_7": -30, "diff_netchangers_30": -34, "diff_netchangers_365": 137, "diff_netchangers_7": 8, "diff_netclosed_30": -67, "diff_netclosed_365": 607, "diff_netclosed_7": -10, "diff_netclosers_30": -15, "diff_netclosers_365": 50, "diff_netclosers_7": -3, "diff_netopened_30": -468, "diff_netopened_365": 1676, "diff_netopened_7": -16, "diff_netopeners_30": -39, "diff_netopeners_365": 118, "diff_netopeners_7": -2, "domains": 2, "first_date": "2015-01-31", "last_date": "2015-11-05", "opened": 1676, "opened_30": 171, "opened_365": 1676, "opened_7": 25, "openers": 118, "openers_30": 35, "openers_365": 118, "openers_7": 12, "organizations": 16, "percentage_bmitickets_30": 150, "percentage_bmitickets_365": 0, "percentage_bmitickets_7": 16, "percentage_changed_30": 50, "percentage_changed_365": 0, "percentage_changed_7": 29, "percentage_changers_30": 34, "percentage_changers_365": 0, "percentage_changers_7": 47, "percentage_closed_30": 34, "percentage_closed_365": 0, "percentage_closed_7": 50, "percentage_closers_30": 42, "percentage_closers_365": 0, "percentage_closers_7": 42, "percentage_opened_30": 73, "percentage_opened_365": 0, "percentage_opened_7": 39, "percentage_openers_30": 52, "percentage_openers_365": 0, "percentage_openers_7": 14, "trackers": 31, "type": "jira", "url": "https://jira.opnfv.org/browse/APEX"}