{"changed": [1635, 333], "changed_30": [61, 76], "changed_365": [198, 592], "changed_7": [37, 7], "changers": [122, 20], "changers_30": [13, 0], "changers_365": [37, 0], "changers_7": [5, 0], "closed": [656, 123], "closed_30": [56, 0], "closed_365": [95, 157], "closed_7": [6, 0], "closers": [49, 8], "closers_30": [5, 0], "closers_365": [1, 16], "closers_7": [1, 0], "diff_netchanged_30": [-120, 76], "diff_netchanged_365": [198, 592], "diff_netchanged_7": [8, 7], "diff_netchangers_30": [12, -13], "diff_netchangers_365": [37, 0], "diff_netchangers_7": [4, -4], "diff_netclosed_30": [38, -8], "diff_netclosed_365": [95, 157], "diff_netclosed_7": [3, -1], "diff_netclosers_30": [4, -3], "diff_netclosers_365": [1, 16], "diff_netclosers_7": [0, -1], "diff_netopened_30": [31, -27], "diff_netopened_365": [396, 0], "diff_netopened_7": [-15, -16], "diff_netopeners_30": [0, 2], "diff_netopeners_365": [31, 0], "diff_netopeners_7": [0, 0], "name": ["", "None"], "opened": [1662, 294], "opened_30": [47, 0], "opened_365": [396, 0], "opened_7": [8, 0], "openers": [107, 16], "openers_30": [1, 9], "openers_365": [31, 0], "openers_7": [1, 4], "percentage_changed_30": [66, 0], "percentage_changed_365": [0, 0], "percentage_changed_7": [27, 0], "percentage_changers_30": [1200, 100], "percentage_changers_365": [0, 0], "percentage_changers_7": [400, 100], "percentage_closed_30": [211, 100], "percentage_closed_365": [0, 0], "percentage_closed_7": [100, 100], "percentage_closers_30": [400, 100], "percentage_closers_365": [0, 0], "percentage_closers_7": [0, 100], "percentage_opened_30": [193, 100], "percentage_opened_365": [0, 0], "percentage_opened_7": [65, 100], "percentage_openers_30": [0, 28], "percentage_openers_365": [0, 0], "percentage_openers_7": [0, 0], "trackers": [31, 14]}