{"changed": [351, 478, 235, 148, 107, 53, 31, 46, 64, 18, 5], "changed_30": [93, 74, 66, 40, 11, 9, 0, 11, 17, 12, 2], "changed_365": [351, 478, 235, 148, 107, 53, 31, 46, 64, 18, 5], "changed_7": [6, 23, 34, 12, 0, 0, 0, 9, 6, 0, 0], "changers": [20, 13, 8, 3, 1, 2, 1, 1, 3, 1, 1], "changers_30": [8, 7, 5, 2, 1, 2, 0, 1, 1, 1, 1], "changers_365": [20, 13, 8, 3, 1, 2, 1, 1, 3, 1, 1], "changers_7": [1, 5, 4, 2, 0, 0, 0, 1, 1, 0, 0], "closed": [152, 138, 111, 56, 56, 22, 21, 12, 6, 3, 1], "closed_30": [66, 22, 10, 2, 0, 1, 0, 2, 2, 2, 0], "closed_365": [152, 138, 111, 56, 56, 22, 21, 12, 6, 3, 1], "closed_7": [0, 9, 3, 2, 0, 0, 0, 1, 1, 0, 0], "closers": [11, 8, 4, 3, 1, 1, 1, 1, 1, 1, 1], "closers_30": [4, 5, 2, 1, 0, 1, 0, 1, 1, 1, 0], "closers_365": [11, 8, 4, 3, 1, 1, 1, 1, 1, 1, 1], "closers_7": [0, 3, 1, 1, 0, 0, 0, 1, 1, 0, 0], "diff_netchanged_30": [43, -18, 12, -10, -12, -9, 0, 10, 8, 11, 2], "diff_netchanged_365": [351, 478, 235, 148, 107, 53, 31, 46, 64, 18, 5], "diff_netchanged_7": [-7, 6, 3, 9, -8, -3, 0, 9, 6, -2, 0], "diff_netchangers_30": [0, -1, 0, -1, 0, 1, 0, 0, -2, 0, 1], "diff_netchangers_365": [20, 13, 8, 3, 1, 2, 1, 1, 3, 1, 1], "diff_netchangers_7": [-2, 2, 2, 0, -1, -1, 0, 1, 1, -1, 0], "diff_netclosed_30": [51, -8, -20, -15, -1, -8, 0, 2, 0, 2, 0], "diff_netclosed_365": [152, 138, 111, 56, 56, 22, 21, 12, 6, 3, 1], "diff_netclosed_7": [-1, 9, 0, 2, 0, -1, 0, 1, 1, 0, 0], "diff_netclosers_30": [0, 0, 0, -2, -1, 0, 0, 1, 0, 1, 0], "diff_netclosers_365": [11, 8, 4, 3, 1, 1, 1, 1, 1, 1, 1], "diff_netclosers_7": [-1, 3, 0, 1, 0, -1, 0, 1, 1, 0, 0], "diff_netopened_30": [-3, 22, 24, -2, -6, -2, 0, 0, 0, 0, 1], "diff_netopened_365": [291, 399, 178, 122, 73, 50, 19, 41, 50, 6, 2], "diff_netopened_7": [2, 1, -12, 2, -1, -1, 0, 0, 1, 0, -1], "diff_netopeners_30": [-2, 1, -2, 0, 0, 0, 0, 0, 0, 0, 1], "diff_netopeners_365": [19, 10, 7, 3, 2, 2, 1, 1, 3, 1, 1], "diff_netopeners_7": [2, 1, 0, -1, -1, -1, 0, 0, 1, 0, -1], "name": ["Huawei", "Ericsson", "Intel", "Orange", "Red Hat", "AT&T", "Cloudbase Solutions", "NEC", "Cisco", "Canonical, Ltd.", "Mirantis"], "opened": [291, 399, 178, 122, 73, 50, 19, 41, 50, 6, 2], "opened_30": [36, 43, 41, 10, 2, 5, 0, 0, 1, 0, 1], "opened_365": [291, 399, 178, 122, 73, 50, 19, 41, 50, 6, 2], "opened_7": [11, 14, 9, 4, 0, 0, 0, 0, 1, 0, 0], "openers": [19, 10, 7, 3, 2, 2, 1, 1, 3, 1, 1], "openers_30": [6, 4, 2, 3, 1, 1, 0, 0, 1, 0, 1], "openers_365": [19, 10, 7, 3, 2, 2, 1, 1, 3, 1, 1], "openers_7": [4, 3, 1, 1, 0, 0, 0, 0, 1, 0, 0], "percentage_changed_30": [86, 19, 22, 19, 52, 50, 0, 1000, 88, 1100, 0], "percentage_changed_365": [0, 0, 0, 0, 0, 0, 0, 0, 0, 0, 0], "percentage_changed_7": [53, 35, 9, 300, 100, 100, 0, 0, 0, 100, 0], "percentage_changers_30": [0, 12, 0, 33, 0, 100, 0, 0, 66, 0, 0], "percentage_changers_365": [0, 0, 0, 0, 0, 0, 0, 0, 0, 0, 0], "percentage_changers_7": [66, 66, 100, 0, 100, 100, 0, 0, 0, 100, 0], "percentage_closed_30": [340, 26, 66, 88, 100, 88, 0, 0, 0, 0, 0], "percentage_closed_365": [0, 0, 0, 0, 0, 0, 0, 0, 0, 0, 0], "percentage_closed_7": [100, 0, 0, 0, 0, 100, 0, 0, 0, 0, 0], "percentage_closers_30": [0, 0, 0, 66, 100, 0, 0, 0, 0, 0, 0], "percentage_closers_365": [0, 0, 0, 0, 0, 0, 0, 0, 0, 0, 0], "percentage_closers_7": [100, 0, 0, 0, 0, 100, 0, 0, 0, 0, 0], "percentage_opened_30": [7, 104, 141, 16, 75, 28, 0, 0, 0, 0, 0], "percentage_opened_365": [0, 0, 0, 0, 0, 0, 0, 0, 0, 0, 0], "percentage_opened_7": [22, 7, 57, 100, 100, 100, 0, 0, 0, 0, 100], "percentage_openers_30": [25, 33, 50, 0, 0, 0, 0, 0, 0, 0, 0], "percentage_openers_365": [0, 0, 0, 0, 0, 0, 0, 0, 0, 0, 0], "percentage_openers_7": [100, 50, 0, 50, 100, 100, 0, 0, 0, 0, 100], "trackers": [14, 19, 5, 3, 7, 8, 3, 5, 5, 2, 2]}