{"actions": 94121, "added_lines": 26643410.0, "added_lines_30": 105770, "added_lines_365": 26643410, "added_lines_7": 22344, "authors": 122, "authors_30": 50, "authors_365": 122, "authors_7": 16, "avg_commits_author": 17.71, "avg_commits_month": 210.7, "avg_files_author": 672.4, "avg_files_month": 8001.6, "branches": 4, "commits": 2107, "commits_30": 279, "commits_365": 2107, "commits_7": 67, "committers": 122, "core": 27, "diff_netadded_lines_30": -641561, "diff_netadded_lines_365": 26643410, "diff_netadded_lines_7": 13544, "diff_netauthors_30": -23, "diff_netauthors_365": 122, "diff_netauthors_7": -11, "diff_netcommits_30": -37, "diff_netcommits_365": 2107, "diff_netcommits_7": -1, "diff_netfiles_30": -4796, "diff_netfiles_365": 80016, "diff_netfiles_7": 1267, "diff_netnewauthors_30": -17, "diff_netnewauthors_365": 122, "diff_netnewauthors_7": -1, "diff_netremoved_lines_30": -356582, "diff_netremoved_lines_365": 1190925, "diff_netremoved_lines_7": 230701, "domains": 38, "files": 80016, "files_30": 2685, "files_365": 80016, "files_7": 1555, "first_date": "2014-12-11", "last_date": "2015-11-27", "newauthors": 122, "newauthors_30": 4, "newauthors_365": 122, "newauthors_7": 0, "occasional": 60, "organizations": 19, "percentage_added_lines_30": 85, "percentage_added_lines_365": 0, "percentage_added_lines_7": 153, "percentage_authors_30": 31, "percentage_authors_365": 0, "percentage_authors_7": 40, "percentage_commits_30": 11, "percentage_commits_365": 0, "percentage_commits_7": 1, "percentage_files_30": 64, "percentage_files_365": 0, "percentage_files_7": 439, "percentage_newauthors_30": 80, "percentage_newauthors_365": 0, "percentage_newauthors_7": 100, "percentage_removed_lines_30": 52, "percentage_removed_lines_365": 0, "percentage_removed_lines_7": 851, "regular": 32, "removed_lines": 1190925.0, "removed_lines_30": 322442, "removed_lines_365": 1190925, "removed_lines_7": 257805, "repositories": 38, "type": "git", "url": "https://git.opnfv.org/escalator"}